[
   {
      "id":1,
      "name":"fireSlime",
      "maxhp":10,
      "type":"fire",
      "attackRange":10,
      "Damage":2,
      "attackSpeed":2,
      "weakness":"water",
      "rewards":"fireStone",
      "prefabPath":null
   },
   {
      "id":2,
      "name":"waterSlime",
      "maxhp":10,
      "type":"water",
      "attackRange":15,
      "Damage":1,
      "attackSpeed":2,
      "weakness":"soil",
      "rewards":"waterStone",
      "prefabPath":null
   },
   {
      "id":3,
      "name":"soilSlime",
      "maxhp":20,
      "type":"soil",
      "attackRange":10,
      "Damage":1,
      "attackSpeed":2,
      "weakness":"wind",
      "rewards":"soilStone",
      "prefabPath":null
   },
   {
      "id":4,
      "name":"bossDefener",
      "maxhp":100,
      "type":"all",
      "attackRange":30,
      "Damage":3,
      "attackSpeed":1,
      "weakness":"all",
      "rewards":"key",
      "prefabPath":null
   }
]